indexhtmlappender/__init__.py
indexhtmlappender/__main__.py
indexhtmlappender/cli.py
indexhtmlappender/gui.py
indexhtmlappender/tests/__init__.py
indexhtmlappender/tests/conftest.py
indexhtmlappender/tests/test_utils.py
indexhtmlappender/utils.py
indexhtmlappender-0.6.0.dist-info/LICENSE.md
indexhtmlappender-0.6.0.dist-info/METADATA
indexhtmlappender-0.6.0.dist-info/WHEEL
indexhtmlappender-0.6.0.dist-info/entry_points.txt
indexhtmlappender-0.6.0.dist-info/RECORD
