Metadata-Version: 2.1
Name: indexhtmlappender
Version: 0.6.0
Summary: For each html file you encounter, add the suffix '/index.html' to each relative url
Home-page: https://pypi.org/project/indexhtmlappender
License: MIT
Author: William Bonvini
Author-email: william.bonvini@outlook.com
Requires-Python: >=3.9,<4.0
Classifier: Development Status :: 1 - Planning
Classifier: License :: OSI Approved :: MIT License
Classifier: Natural Language :: English
Classifier: Operating System :: OS Independent
Classifier: Programming Language :: Python
Classifier: Programming Language :: Python :: 3
Classifier: Programming Language :: Python :: 3.9
Classifier: Programming Language :: Python :: 3.10
Classifier: Programming Language :: Python :: 3.11
Requires-Dist: minilog
Requires-Dist: typer (>=0.9.0,<0.10.0)
Project-URL: Documentation, https://indexhtmlappender.readthedocs.io
Project-URL: Repository, https://github.com/WilliamBonvini/indexhtmlappender
